Workbook

Sheet Summary
A1: Prompt Engineering Summary
A2: Task 3.3 -- Skill Set Go EduTech ML Internship | Imangali Bayangaliyev
A4: Model tested | B4: Sonnet 5.5 Claude
A5: Date run | B5: 2026-10-05
A6: Method | B6: Four use cases. Same model, fresh chat for every run, test inputs identical across versions, scoring rules and answer keys fixed before running. One run per prompt version.
A8: Use case | B8: Content V1 | C8: Content V2 | D8: Change | E8: Format V1 | F8: Format V2 | G8: Change | H8: Verdict
A9: Reasoning | B9: ='Evaluation Log'!L5 -> 1 | C9: ='Evaluation Log'!L6 -> 1 | D9: =C9-B9 -> 0 | E9: ='Evaluation Log'!M5 -> 0 | F9: ='Evaluation Log'!M6 -> 1 | G9: =F9-E9 -> 1 | H9: ='Evaluation Log'!O6 -> Improved
A10: Extraction | B10: ='Evaluation Log'!L7 -> 1 | C10: ='Evaluation Log'!L8 -> 1 | D10: =C10-B10 -> 0 | E10: ='Evaluation Log'!M7 -> 0 | F10: ='Evaluation Log'!M8 -> 1 | G10: =F10-E10 -> 1 | H10: ='Evaluation Log'!O8 -> Improved
A11: Summarization | B11: ='Evaluation Log'!L9 -> 1 | C11: ='Evaluation Log'!L10 -> 1 | D11: =C11-B11 -> 0 | E11: ='Evaluation Log'!M9 -> 0 | F11: ='Evaluation Log'!M10 -> 1 | G11: =F11-E11 -> 1 | H11: ='Evaluation Log'!O10 -> Improved
A12: Coding | B12: ='Evaluation Log'!L11 -> 0.8 | C12: ='Evaluation Log'!L12 -> 1 | D12: =C12-B12 -> 0.2 | E12: ='Evaluation Log'!M11 -> 0 | F12: ='Evaluation Log'!M12 -> 1 | G12: =F12-E12 -> 1 | H12: ='Evaluation Log'!O12 -> Improved
A13: Green = linked from 'Evaluation Log'. Percentages are score / max for each use case.
A15: Key findings
A16: 1. Correctness was already at or near ceiling in V1 for three of four use cases (reasoning, extraction, summarization). The test sets were too easy to separate prompts on correctness; this is reported as a finding, not hidden.
A17: 2. The measurable gain from prompt iteration was output control: exact answer lines, fixed JSON schemas, length limits and return-type contracts moved format/constraint compliance from 0% to 100% in every use case.
A18: 3. Coding was the only case where V1 was not fully correct. The failure traced to an unstated requirement (return type and empty-input behaviour), not to faulty logic. Specifying the contract fixed it.
A19: 4. Explicit null rules held up: in extraction, the model returned null for the missing ticker and date in both versions instead of inventing values.
A20: 5. In summarization, cutting from roughly 50 words to 40 or fewer did not drop any key fact on this test set.
A22: Limitations
A23: - One run per prompt version on one model: results do not show output stability or generalise to other models.
A24: - Small fixed test sets (3 inputs per use case, 5 unit tests for coding); high scores here do not mean the prompts are robust on harder inputs.
A25: - Scoring was strict by design; some format failures (for example the missing 'Answer:' line) are judgement-sensitive if read leniently.
A26: - Maximum scores differ by use case, so percentages are comparable within a use case, not across use cases.

Sheet Evaluation Log
A1: Task 3.3 - Prompt Evaluation Sheet: iterations and outcomes
A2: Blue = scores entered by hand after running the fixed tests. Black = formulas. Full prompt text and raw outputs are in 'Prompts & Outputs'; scoring rules and answer keys are in 'Rules & Keys'.
A4: Run ID | B4: Use case | C4: Version | D4: Prompt design | E4: Test inputs (fixed across versions) | F4: Content metric | G4: Content score | H4: Content max | I4: Format / constraint metric | J4: Format score | K4: Format max | L4: Content % | M4: Format % | N4: What changed vs previous version | O4: Result vs previous | P4: Notes
A5: RSN-V1 | B5: Reasoning | C5: V1 | D5: Bare instruction: 'Solve these three problems.' | E5: 3 finance problems (R1 stock return, R2 compounding with withdrawal, R3 Bayes fraud test) | F5: Correct final answers (/3) | G5: 3 | H5: 3 | I5: Ends with exact 'Answer:' line (/3) | J5: 0 | K5: 3 | L5: =IF(H5=0,0,G5/H5) -> 1 | M5: =IF(K5=0,0,J5/K5) -> 0 | N5: Baseline. | O5: Baseline | P5: Correct and well explained, but no 'Answer:' lines. Scored strictly against the rule fixed before running; a lenient reader might give partial format credit. Ceiling effect: the baseline was already fully correct, so the test set could not separate prompts on correctness.
A6: RSN-V2 | B6: Reasoning | C6: V2 | D6: Role + max 4 calculation lines + state assumptions + rounding rules + strict 'Answer: <value>' line + no trailing commentary | E6: Same 3 problems | F6: Correct final answers (/3) | G6: 3 | H6: 3 | I6: Ends with exact 'Answer:' line (/3) | J6: 3 | K6: 3 | L6: =IF(H6=0,0,G6/H6) -> 1 | M6: =IF(K6=0,0,J6/K6) -> 1 | N6: Added role, 4-line cap, assumption statements, rounding rules, strict Answer line. | O6: =IF(AND(L6=L5,M6=M5),"No change",IF(AND(L6>=L5,M6>=M5),"Improved","Mixed / degraded")) -> Improved | P6: Correctness unchanged (already at ceiling); gain is controllable, machine-readable output. Assumptions made explicit (e.g. withdrawal timing in R2).
A7: EXT-V1 | B7: Extraction | C7: V1 | D7: Names the five fields in plain language, no schema: 'Extract the company, ticker, event type, amount, and date ... as JSON.' | E7: 3 news snippets (E1 earnings, E2 acquisition with no ticker/exact date, E3 dividend) | F7: Fields matching gold key (/15) | G7: 15 | H7: 15 | I7: Valid JSON with exactly the 5 keys, nothing else (/3) | J7: 0 | K7: 3 | L7: =IF(H7=0,0,G7/H7) -> 1 | M7: =IF(K7=0,0,J7/K7) -> 0 | N7: Baseline. | O7: Baseline | P7: All values correct, and the model correctly returned null for the missing ticker and date in E2 (no invented values). 'amount' was accepted as equal to 'amount_usd' because V1 never named the keys. Format fails: extra keys (exchange, currency, target, *_description) and non-specified key names. Ceiling effect on correctness.
A8: EXT-V2 | B8: Extraction | C8: V2 | D8: Role + exact 5-key schema + enum for event_type + plain-number amounts + ISO dates + 'use null, never guess' + JSON-only output | E8: Same 3 snippets | F8: Fields matching gold key (/15) | G8: 15 | H8: 15 | I8: Valid JSON with exactly the 5 keys, nothing else (/3) | J8: 3 | K8: 3 | L8: =IF(H8=0,0,G8/H8) -> 1 | M8: =IF(K8=0,0,J8/K8) -> 1 | N8: Added exact schema, null rule, number and date formats, event_type enum, JSON-only rule. | O8: =IF(AND(L8=L7,M8=M7),"No change",IF(AND(L8>=L7,M8>=M7),"Improved","Mixed / degraded")) -> Improved | P8: Output parses directly and has a fixed shape. Null handling held on E2. Correctness unchanged; improvement is in format and parseability, which is what downstream code needs.
A9: SUM-V1 | B9: Summarization | C9: V1 | D9: Bare instruction: 'Summarize each of the three passages below.' | E9: 3 short finance passages (S1 bank earnings, S2 central bank decision, S3 failed drug trial) | F9: Key facts present with correct figures (/9) | G9: 9 | H9: 9 | I9: Each summary at most 40 words (/3) | J9: 0 | K9: 3 | L9: =IF(H9=0,0,G9/H9) -> 1 | M9: =IF(K9=0,0,J9/K9) -> 0 | N9: Baseline. | O9: Baseline | P9: All 9 checklist facts present, no hallucinations. Word counts: 43, 55, 53 (limit was not stated in V1, so this is the expected baseline failure). Output used bold labels 'Passage N'.
A10: SUM-V2 | B10: Summarization | C10: V2 | D10: Role + 40-word cap + lead with main development + keep numbers exactly + no outside context + fixed labels, nothing else | E10: Same 3 passages | F10: Key facts present with correct figures (/9) | G10: 9 | H10: 9 | I10: Each summary at most 40 words (/3) | J10: 3 | K10: 3 | L10: =IF(H10=0,0,G10/H10) -> 1 | M10: =IF(K10=0,0,J10/K10) -> 1 | N10: Added 40-word cap, 'lead with most important development', keep-numbers-exactly rule, label format. | O10: =IF(AND(L10=L9,M10=M9),"No change",IF(AND(L10>=L9,M10>=M9),"Improved","Mixed / degraded")) -> Improved | P10: Word counts: 37, 39, 40 (S3 sits exactly at the limit; passes under the 'at most 40' rule). Compression did not cost any key facts. No hallucinations.
A11: COD-V1 | B11: Coding | C11: V1 | D11: Bare instruction: 'Write a Python function that calculates the maximum drawdown of a list of prices.' | E11: 5 unit tests on max_drawdown (falling+recovery, monotonic rise, single price, empty list, double drawdown) | F11: Tests with correct drawdown value (/5) | G11: 4 | H11: 5 | I11: Contract: returns plain float (1) and 0.0 on empty list (1) (/2) | J11: 0 | K11: 2 | L11: =IF(H11=0,0,G11/H11) -> 0.8 | M11: =IF(K11=0,0,J11/K11) -> 0 | N11: Baseline. | O11: Baseline | P11: Algorithm correct on all non-empty cases (response also ran the 30.77% example correctly and its pandas one-liner matched). Fails the empty-list test because it raises ValueError; returns a tuple (mdd, peak_idx, trough_idx), so the value was read from element 0. Both are unspecified-requirement gaps in the prompt, not logic errors. Added unrequested extras (pandas version, recovery-time suggestion).
A12: COD-V2 | B12: Coding | C12: V2 | D12: Role + exact signature with type hints + return plain float in [0,1] + empty list -> 0.0, no error + stdlib only, single pass + docstring + code block only | E12: Same 5 unit tests | F12: Tests with correct drawdown value (/5) | G12: 5 | H12: 5 | I12: Contract: returns plain float (1) and 0.0 on empty list (1) (/2) | J12: 2 | K12: 2 | L12: =IF(H12=0,0,G12/H12) -> 1 | M12: =IF(K12=0,0,J12/K12) -> 1 | N12: Added exact signature, return type, empty-list rule, stdlib/single-pass constraint, code-only output. | O12: =IF(AND(L12=L11,M12=M11),"No change",IF(AND(L12>=L11,M12>=M11),"Improved","Mixed / degraded")) -> Improved | P12: All 5 tests pass and return type is float. Unrequested behaviour noted for audit: non-positive peaks are silently skipped to avoid division by zero. First use case where V1 was not fully correct; the cause was an unstated specification.
A14: Scoring convention: Content = correctness / key-fact coverage; Format = output-format or constraint compliance. Rules were fixed before each run. Maximums differ by use case.

Sheet Rules & Keys
A1: Scoring rules and answer keys (fixed before each run)
A3: Use case | B3: Item | C3: Rule / key
A4: Reasoning | B4: Correctness (1 per problem) | C4: R1 correct if answer is 0% (no change). R2 correct if within $1 of $11,135.06. R3 correct if between 15.5% and 16.5% (exact about 16.1%).
A5: Reasoning | B5: Format (1 per problem) | C5: Response ends each problem with a line starting 'Answer:' containing only the final value.
A6: Reasoning | B6: Key | C6: R1: 0.80 x 1.25 = 1.00 -> 0%. R2: 10,000 x 1.06^3 = 11,910.16; minus 2,000 = 9,910.16; x 1.06^2 = 11,135.06. R3: Bayes: 0.0095 / (0.0095 + 0.0495) = 0.161.
A7: Extraction | B7: Correctness (1 per field, 15 total) | C7: Field matches gold key. Strings compared case-insensitively. Amounts must be numbers (not text like '$4.2 billion'). A non-null value where the key says null counts as wrong and is flagged as invented.
A8: Extraction | B8: Format (1 per snippet) | C8: Valid JSON with exactly the five keys (company, ticker, event_type, amount_usd, date) and no extra text.
A9: Extraction | B9: Gold key E1 | C9: company Apex Semiconductor | ticker APXS | event_type earnings | amount_usd 4200000000 | date 2025-10-28
A10: Extraction | B10: Gold key E2 | C10: company Beta Holdings | ticker null | event_type acquisition | amount_usd 850000000 | date null ('Tuesday' is not an exact date)
A11: Extraction | B11: Gold key E3 | C11: company Nordwind Energy | ticker NWE | event_type dividend | amount_usd 0.42 | date 2025-12-01
A12: Summarization | B12: Coverage (1 per fact, 9 total) | C12: Key fact present with the correct number.
A13: Summarization | B13: Constraint (1 per summary) | C13: Summary is 40 words or fewer (words counted by whitespace split).
A14: Summarization | B14: Accuracy | C14: Any figure or claim not in the passage is flagged as a hallucination.
... A18: Coding | B18: Unit tests | C18: [100,120,90,95,80,110] -> 1/3; [100,110,120,130] -> 0.0; [50] -> 0.0; [] -> 0.0; [100,50,100,25] -> 0.75

Sheet Prompts & Outputs
A1: Full prompts and raw model outputs (verbatim)
A3: Run ID | B3: Prompt (verbatim) | C3: Model output (verbatim)
A4: RSN-V1 | B4: Solve these three problems. 1. A stock falls 20% in January and rises 25% in February. What is the net percentage change over the two months? 2. An investor puts $10,000 in an account earning 6% per year, compounded annually. After 3 years she withdraws $2,000 and leaves the rest for 2 more years at the same rate. What is the final balance? 3. A fraud test flags 95% of fraudulent transactions and also wrongly flags 5% of legitimate ones. If 1% of all transactions are fraudulent, what is the probability that a flagged transaction is actually fraud? | C4: 1. Net change: 0% 0.80 × 1.25 = 1.00, so the stock ends exactly where it started. The 25% gain is on a smaller base, which is why it only offsets the 20% loss instead of beating it. 2. Final balance: $11,135.06 * After 3 years: $10,000 × 1.06³ = $11,910.16 * After the $2,000 withdrawal: $9,910.16 * After 2 more years: $9,910.16 × 1.06² = $9,910.16 × 1.1236 = $11,135.06 3. Probability a flagged transaction is fraud: about 16.1% Use Bayes' theorem: * Fraud that gets flagged: 0.95 × 0.01 = 0.0095 * Legitimate transactions that get flagged: 0.05 × 0.99 = 0.0495 * All flagged transactions: 0.0095 + 0.0495 = 0.059 * P(fraud | flagged) = 0.0095 / 0.059 ≈ 0.161 Fraud is rare at 1%, so the false alarms on the other 99% of transactions far outnumber the real catches. About 5 out of every 6 flags are false positives.
A5: RSN-V2 | B5: You are a careful quantitative analyst. Solve each problem below. Rules: - Show your calculation briefly, in at most 4 short lines per problem. - State any assumption you make. - Give percentages to 1 decimal place and dollar amounts to the cent. - End each problem with a line in exactly this form: "Answer: <final value only>" - Do not add any commentary after the Answer line. 1. A stock falls 20% in January and rises 25% in February. What is the net percentage change over the two months? 2. An investor puts $10,000 in an account earning 6% per year, compounded annually. After 3 years she withdraws $2,000 and leaves the rest for 2 more years at the same rate. What is the final balance? 3. A fraud test flags 95% of fraudulent transactions and also wrongly flags 5% of legitimate ones. If 1% of all transactions are fraudulent, what is the probability that a flagged transaction is actually fraud? | C5: 1. Assumption: the 25% rise applies to the price at the end of January. 0.80 × 1.25 = 1.00 Net change = 1.00 − 1 = 0 Answer: 0.0% 2. Assumption: the withdrawal happens at the very end of year 3, after that year's interest is added. 10,000 × 1.06³ = 11,910.16 11,910.16 − 2,000 = 9,910.16 9,910.16 × 1.06² = 9,910.16 × 1.1236 = 11,135.06 Answer: $11,135.06 3. Assumption: the 95% and 5% flag rates hold for every transaction, so Bayes' theorem applies. P(flagged and fraud) = 0.01 × 0.95 = 0.0095 P(flagged and legitimate) = 0.99 × 0.05 = 0.0495 P(fraud | flagged) = 0.0095 / (0.0095 + 0.0495) = 0.0095 / 0.0590 = 0.1610 Answer: 16.1%
A6: EXT-V1 | B6: Extract the company, ticker, event type, amount, and date from each of the three news snippets below as JSON. Snippet 1: Apex Semiconductor (NASDAQ: APXS) reported third-quarter revenue of $4.2 billion on October 28, 2025, up 12% from a year earlier. Snippet 2: Beta Holdings, a privately held logistics firm, agreed to acquire Corvane Freight for about $850 million, the companies said Tuesday. Snippet 3: Nordwind Energy (NYSE: NWE) will pay a quarterly dividend of $0.42 per share to holders of record on December 1, 2025. | C6: [ { "company": "Apex Semiconductor", "ticker": "APXS", "exchange": "NASDAQ", "event_type": "earnings", "amount": 4200000000, "currency": "USD", "amount_description": "Q3 revenue (up 12% YoY)", "date": "2025-10-28", "date_description": "report date" }, { "company": "Beta Holdings", "ticker": null, "exchange": null, "event_type": "acquisition", "target": "Corvane Freight", "amount": 850000000, "currency": "USD", "amount_description": "approximate deal value", "date": null, "date_description": "announced \"Tuesday\" (exact date not given)" }, { "company": "Nordwind Energy", "ticker": "NWE", "exchange": "NYSE", "event_type": "dividend", "amount": 0.42, "currency": "USD", "amount_description": "quarterly dividend per share", "date": "2025-12-01", "date_description": "record date" } ]
A7: EXT-V2 | B7: You are a data extraction system for financial news. For each of the three snippets below, extract exactly these five fields and return a JSON array with one object per snippet, in order: - "company": company name only, no ticker or suffix - "ticker": ticker symbol only (e.g. "ABC"), or null if the text does not state one - "event_type": one of "earnings", "acquisition", "dividend", "other" - "amount_usd": a plain number in US dollars (e.g. 4200000000, not "$4.2 billion"), or null if no amount is stated - "date": ISO format YYYY-MM-DD, or null if the text does not give an exact calendar date Rules: - Use only information stated in the snippet. Never guess or infer a missing value; use null. - Use exactly these five keys and no others. - Output only the JSON array, with no explanation and no markdown code fences. Snippet 1: Apex Semiconductor (NASDAQ: APXS) reported third-quarter revenue of $4.2 billion on October 28, 2025, up 12% from a year earlier. Snippet 2: Beta Holdings, a privately held logistics firm, agreed to acquire Corvane Freight for about $850 million, the companies said Tuesday. Snippet 3: Nordwind Energy (NYSE: NWE) will pay a quarterly dividend of $0.42 per share to holders of record on December 1, 2025. | C7: [{"company":"Apex Semiconductor","ticker":"APXS","event_type":"earnings","amount_usd":4200000000,"date":"2025-10-28"},{"company":"Beta Holdings","ticker":null,"event_type":"acquisition","amount_usd":850000000,"date":null},{"company":"Nordwind Energy","ticker":"NWE","event_type":"dividend","amount_usd":0.42,"date":"2025-12-01"}]
A8: SUM-V1 | B8: Summarize each of the three passages below. Passage 1: Orion Bank reported second-quarter net income of $1.8 billion, up 9% from last year, helped by higher interest income. Fee income fell 4% as trading activity slowed. The bank set aside $320 million for expected loan losses, double the previous quarter, citing weaker commercial real estate. It kept its full-year profit forecast unchanged. Passage 2: The central bank held its benchmark interest rate at 4.5% on Wednesday, the third consecutive meeting without a change. Policymakers said inflation had eased to 3.1% but remained above the 2% target. Two of nine members voted for a cut. The governor said rates would stay restrictive until inflation is clearly heading to target, and gave no timeline for cuts. Passage 3: Helix Pharma's stock fell 22% on Thursday after a late-stage trial of its lead cancer drug missed its main goal. The drug extended survival by 1.2 months against a required 3 months. The company said it would review the data with regulators but cut its full-year revenue forecast by $400 million. Analysts at two brokerages downgraded the stock. | C8: **Passage 1:** Orion Bank's second-quarter profit rose 9% to $1.8 billion, driven by higher interest income, though fee income dropped 4% on slower trading. It doubled loan-loss provisions to $320 million because of weakness in commercial real estate, and it left its full-year forecast unchanged. **Passage 2:** The central bank kept rates at 4.5% for a third meeting in a row. Inflation has eased to 3.1%, but that's still above the 2% target. Two of the nine members voted for a cut. The governor said policy will stay restrictive until inflation is clearly heading to target and gave no timeline for cuts. **Passage 3:** Helix Pharma shares fell 22% after its lead cancer drug missed its main goal in a late-stage trial. It extended survival by 1.2 months, well short of the required 3. The company will review the data with regulators, but it cut its revenue forecast by $400 million, and two brokerages downgraded the stock.
A9: SUM-V2 | B9: You are a financial news editor writing summaries for busy investors. Summarize each of the three passages below in at most 40 words each. Rules: - Lead with the single most important development. - Keep every key number (percentages, dollar amounts, rates) exactly as written in the passage. - Use only information stated in the passage. Do not add opinion or outside context. - Label the summaries "Summary 1", "Summary 2", "Summary 3", and output nothing else. Passage 1: Orion Bank reported second-quarter net income of $1.8 billion, up 9% from last year, helped by higher interest income. Fee income fell 4% as trading activity slowed. The bank set aside $320 million for expected loan losses, double the previous quarter, citing weaker commercial real estate. It kept its full-year profit forecast unchanged. Passage 2: The central bank held its benchmark interest rate at 4.5% on Wednesday, the third consecutive meeting without a change. Policymakers said inflation had eased to 3.1% but remained above the 2% target. Two of nine members voted for a cut. The governor said rates would stay restrictive until inflation is clearly heading to target, and gave no timeline for cuts. Passage 3: Helix Pharma's stock fell 22% on Thursday after a late-stage trial of its lead cancer drug missed its main goal. The drug extended survival by 1.2 months against a required 3 months. The company said it would review the data with regulators but cut its full-year revenue forecast by $400 million. Analysts at two brokerages downgraded the stock. | C9: Summary 1 Orion Bank's second-quarter net income rose 9% to $1.8 billion, helped by higher interest income. Fee income fell 4% as trading slowed. Loan-loss provisions doubled to $320 million on weaker commercial real estate. Full-year profit forecast unchanged. Summary 2 The central bank held its benchmark rate at 4.5%, its third straight meeting without change. Inflation eased to 3.1%, still above the 2% target. Two of nine members voted for a cut. The governor gave no timeline for cuts. Summary 3 Helix Pharma's stock fell 22% after its lead cancer drug missed its main goal in a late-stage trial, extending survival 1.2 months versus a required 3 months. It cut its full-year revenue forecast by $400 million; two brokerages downgraded it.
A10: COD-V1 | B10: Write a Python function that calculates the maximum drawdown of a list of prices. | C10: This function goes through the prices once, so it runs in O(n) time. It returns the drawdown as a fraction, along with the peak and trough indices. ```python def max_drawdown(prices): """ Calculate the maximum drawdown of a price series. Returns: (mdd, peak_idx, trough_idx) mdd -- largest peak-to-trough decline as a fraction (e.g. 0.25 = -25%) peak_idx -- index of the peak before the worst decline trough_idx -- index of the trough of the worst decline """ if not prices: raise ValueError("prices must be a non-empty list") if any(p <= 0 for p in prices): raise ValueError("prices must be positive") peak_val, peak_idx = prices[0], 0 mdd, best_peak, best_trough = 0.0, 0, 0 for i, p in enumerate(prices): if p > peak_val: peak_val, peak_idx = p, i dd = (peak_val - p) / peak_val if dd > mdd: mdd, best_peak, best_trough = dd, peak_idx, i return mdd, best_peak, best_trough # Example prices = [100, 120, 110, 130, 90, 95, 140, 105] mdd, peak, trough = max_drawdown(prices) print(f"Max drawdown: {mdd:.2%} (peak {prices[peak]} at i={peak}, trough {prices[trough]} at i={trough})") # Max drawdown: 30.77% (peak 130 at i=3, trough 90 at i=4) ``` How it works: - Running peak: it keeps track of the highest price seen so far. - Current drawdown: at each step, it measures how far the price has fallen from that peak. - Worst drawdown: it keeps the largest fall it finds. If you're using pandas: a vectorized version is a one-liner: ```python import pandas as pd def max_drawdown_pd(prices: pd.Series) -> float: return (1 - prices / prices.cummax()).max() ``` For a portfolio tracker: you can also measure how long a drawdown lasts and how long it takes to recover. The recovery point is the first index after the trough where the price gets back to the peak.
A11: COD-V2 | B11: You are a senior quantitative developer writing production-quality Python. Write a function with this exact signature: def max_drawdown(prices: list[float]) -> float Requirements: - Return the maximum drawdown as a single float fraction between 0 and 1 (0.25 means a 25% peak-to-trough fall). Return a plain float, not a tuple. - Drawdown at each point = (running peak - price) / running peak. The result is the largest value. - If the list is empty, return 0.0. Do not raise an error. - If prices never fall below a prior peak (or there is only one price), return 0.0. - Use only the Python standard library and a single pass through the list. - Include a short docstring. Output only one Python code block containing the function. No explanation, no example usage. | C11: def max_drawdown(prices: list[float]) -> float: """Return the maximum peak-to-trough drawdown as a fraction in [0, 1]. Drawdown at each point is (running_peak - price) / running_peak; the result is the largest such value. Returns 0.0 for an empty list, a single price, or a series that never falls below a prior peak. Non-positive peaks are skipped to avoid division by zero. """ max_dd = 0.0 peak = None for price in prices: if peak is None or price > peak: peak = price elif peak > 0: drawdown = (peak - price) / peak if drawdown > max_dd: max_dd = drawdown return float(min(max_dd, 1.0))
